{
  "students": [
    {
      "id": 1,
      "nombre": "Isabella",
      "apellido": "Almada",
      "email": "ialmada@gmail.com",
      "contrasenia": "87654321",
      "telefono": "0342-15680964",
      "documento": 25890752
    },
    {
      "id": 2,
      "nombre": "Walter",
      "apellido": "Milessi",
      "email": "wmilessi@hotmail.com",
      "contrasenia": "67805432",
      "telefono": "0342-154443327",
      "documento": 34896543
    },
    {
      "nombre": "Lucila",
      "apellido": "Brasca",
      "email": "lbrasca@gmail.com",
      "contrasenia": "568jjjooo",
      "telefono": "1237498798",
      "documento": 597595975,
      "id": 3
    }
  ],
  "courses": [
    {
      "nombre": "Angular",
      "fechaInicio": "2023-09-12",
      "fechaFin": "2023-10-25",
      "id": 1
    },
    {
      "nombre": "PHP",
      "fechaInicio": "2024-04-12",
      "fechaFin": "2024-05-18",
      "id": 2
    },
    {
      "nombre": "Angular",
      "fechaInicio": "2023-08-31",
      "fechaFin": "2023-10-18",
      "id": 3
    }
  ],
  "teachers": [
    {
      "id": 1,
      "nombre": "Pedro",
      "apellido": "Albertario",
      "email": "palbert@hotmail.com",
      "courseId": 1
    },
    {
      "nombre": "Maximiliano",
      "apellido": "Perez",
      "email": "mperez@gmail.com",
      "courseId": 3,
      "id": 2
    }
  ],
  "users": [
    {
      "nombre": "Clara",
      "apellido": "Robledo",
      "email": "crobledo@gmail.com",
      "contrasenia": "12345678",
      "rol": "ADMINISTRADOR",
      "token": "7688979hdkyf345",
      "id": 1
    },
    {
      "nombre": "Matias",
      "apellido": "Carrizo",
      "email": "mcarrizo@gmail.com",
      "contrasenia": "87654321",
      "rol": "ADMINISTRADOR",
      "token": "e579o9htdswrkif",
      "id": 2
    },
    {
      "id": 3,
      "nombre": "Sergio",
      "apellido": "Trotta",
      "email": "strotta@hotmail.com",
      "contrasenia": "67805432",
      "token": "7980gfhgfkhdkyf",
      "rol": "USUARIO"
    },
    {
      "nombre": "Guadalupe",
      "apellido": "Barzaghi",
      "email": "gbarza@gmail.com",
      "contrasenia": "guadalupe",
      "rol": "USUARIO",
      "token": "dsvf4sZTfovRx8u",
      "id": 4
    }
  ],
  "registration": [
    {
      "id": 1,
      "studentId": 1,
      "courseId": 1
    },
    {
      "studentId": 2,
      "courseId": 1,
      "id": 5
    },
    {
      "studentId": 1,
      "courseId": 1,
      "id": 6
    }
  ]
}